comprehender/__init__.py
comprehender-0.1.0.dist-info/WHEEL
comprehender-0.1.0.dist-info/METADATA
comprehender-0.1.0.dist-info/RECORD
